examples/usage.py
examples/usage_parallel.py
examples/usage_template_language.py
pgbenchmark/__init__.py
pgbenchmark/benchmark.py
pgbenchmark/benchmark_parallel.py
pgbenchmark/benchmark_threaded.py
pgbenchmark/cli.py
pgbenchmark/server.py
pgbenchmark/visualizer/__init__.py
pgbenchmark/visualizer/main.py
pgbenchmark/visualizer/static/style.css
pgbenchmark-0.1.8.dist-info/licenses/LICENSE
venv/bin/activate_this.py
pgbenchmark-0.1.8.dist-info/METADATA
pgbenchmark-0.1.8.dist-info/WHEEL
pgbenchmark-0.1.8.dist-info/entry_points.txt
pgbenchmark-0.1.8.dist-info/top_level.txt
pgbenchmark-0.1.8.dist-info/RECORD
