Metadata-Version: 2.4
Name: pgbenchmark
Version: 0.1.8
Summary: A Python package to benchmark query performance on PostgreSQL Database.
Author-email: Elguja Lomsadze <lomsadze.guja@gmail.com>
License: Apache License 2.0
Project-URL: Homepage, https://github.com/GujaLomsadze/pgbenchmark
Classifier: Programming Language :: Python :: 3
Classifier: License :: OSI Approved :: Apache Software License
Classifier: Operating System :: OS Independent
Classifier: Development Status :: 3 - Alpha
Classifier: Intended Audience :: Developers
Classifier: Topic :: Database :: Front-Ends
Classifier: Topic :: Software Development :: Testing
Requires-Python: >=3.10
License-File: LICENSE
Requires-Dist: psycopg2-binary==2.9.10
Requires-Dist: SQLAlchemy==2.0.40
Requires-Dist: fastapi==0.115.12
Requires-Dist: uvicorn==0.34.0
Requires-Dist: websockets==15.0.1
Requires-Dist: Jinja2==3.1.6
Dynamic: license-file
